{
  "updated_at": "2026-05-20T17:51:31.531873+00:00",
  "data_referencia": "2026-05-20",
  "airport_icao": "SBEG",
  "airport_name": "Manaus",
  "airport_info": {
    "sg_aerodromo_icao": "SBEG",
    "sg_aerodromo_iata": "MAO",
    "descricao": "EDUARDO GOMES - MANAUS - AM - BRASIL"
  },
  "source": "SIROS/ANAC",
  "source_url": "https://sas.anac.gov.br/sas/siros_api/",
  "arrivals": [
    {
      "callsign": "TAM3750",
      "numero_voo": "3750",
      "airline_icao": "TAM",
      "airline": "LATAM",
      "equipamento_icao": "A321",
      "equipamento": "Airbus A321",
      "assentos": "224",
      "etapa": "1",
      "tipo_operacao": "Domestico",
      "tipo_servico": "REGULAR DE PASSAGEIROS DOMÉSTICA",
      "origem_icao": "SBBR",
      "destino_icao": "SBEG",
      "partida_iso": "2026-05-19T21:20:00-03:00",
      "chegada_iso": "2026-05-20T00:20:00-03:00",
      "partida_brt": "21:20",
      "chegada_brt": "00:20",
      "status": "programado",
      "fonte": "SIROS/ANAC",
      "rota": "SBBR",
      "rota_nome": "Brasilia"
    },
    {
      "callsign": "TAM3189",
      "numero_voo": "3189",
      "airline_icao": "TAM",
      "airline": "LATAM",
      "equipamento_icao": "A320",
      "equipamento": "Airbus A320",
      "assentos": "180",
      "etapa": "1",
      "tipo_operacao": "Domestico",
      "tipo_servico": "REGULAR DE PASSAGEIROS DOMÉSTICA",
      "origem_icao": "SBBE",
      "destino_icao": "SBEG",
      "partida_iso": "2026-05-19T23:20:00-03:00",
      "chegada_iso": "2026-05-20T01:30:00-03:00",
      "partida_brt": "23:20",
      "chegada_brt": "01:30",
      "status": "programado",
      "fonte": "SIROS/ANAC",
      "rota": "SBBE",
      "rota_nome": "Belem"
    },
    {
      "callsign": "AZU2062",
      "numero_voo": "2062",
      "airline_icao": "AZU",
      "airline": "Azul",
      "equipamento_icao": "A21N",
      "equipamento": "Airbus A321neo",
      "assentos": "0",
      "etapa": "1",
      "tipo_operacao": "Domestico",
      "tipo_servico": "REGULAR DE CARGA DOMÉSTICA",
      "origem_icao": "SBKP",
      "destino_icao": "SBEG",
      "partida_iso": "2026-05-19T22:15:00-03:00",
      "chegada_iso": "2026-05-20T02:00:00-03:00",
      "partida_brt": "22:15",
      "chegada_brt": "02:00",
      "status": "programado",
      "fonte": "SIROS/ANAC",
      "rota": "SBKP",
      "rota_nome": "Campinas / Viracopos"
    },
    {
      "callsign": "GLO1544",
      "numero_voo": "1544",
      "airline_icao": "GLO",
      "airline": "GOL",
      "equipamento_icao": "B38M",
      "equipamento": "Boeing 737 MAX 8",
      "assentos": "186",
      "etapa": "1",
      "tipo_operacao": "Domestico",
      "tipo_servico": "REGULAR DE PASSAGEIROS DOMÉSTICA",
      "origem_icao": "SBGR",
      "destino_icao": "SBEG",
      "partida_iso": "2026-05-19T22:40:00-03:00",
      "chegada_iso": "2026-05-20T02:30:00-03:00",
      "partida_brt": "22:40",
      "chegada_brt": "02:30",
      "status": "programado",
      "fonte": "SIROS/ANAC",
      "rota": "SBGR",
      "rota_nome": "Sao Paulo / Guarulhos"
    },
    {
      "callsign": "AZU6103",
      "numero_voo": "6103",
      "airline_icao": "AZU",
      "airline": "Azul",
      "equipamento_icao": "AT76",
      "equipamento": "ATR 72",
      "assentos": "70",
      "etapa": "1",
      "tipo_operacao": "Domestico",
      "tipo_servico": "REGULAR DE PASSAGEIROS DOMÉSTICA",
      "origem_icao": "SBSN",
      "destino_icao": "SBEG",
      "partida_iso": "2026-05-20T00:45:00-03:00",
      "chegada_iso": "2026-05-20T02:30:00-03:00",
      "partida_brt": "00:45",
      "chegada_brt": "02:30",
      "status": "programado",
      "fonte": "SIROS/ANAC",
      "rota": "SBSN",
      "rota_nome": "Santarem"
    },
    {
      "callsign": "AZU2648",
      "numero_voo": "2648",
      "airline_icao": "AZU",
      "airline": "Azul",
      "equipamento_icao": "A21N",
      "equipamento": "Airbus A321neo",
      "assentos": "214",
      "etapa": "1",
      "tipo_operacao": "Domestico",
      "tipo_servico": "REGULAR DE PASSAGEIROS DOMÉSTICA",
      "origem_icao": "SBRF",
      "destino_icao": "SBEG",
      "partida_iso": "2026-05-19T22:30:00-03:00",
      "chegada_iso": "2026-05-20T02:35:00-03:00",
      "partida_brt": "22:30",
      "chegada_brt": "02:35",
      "status": "programado",
      "fonte": "SIROS/ANAC",
      "rota": "SBRF",
      "rota_nome": "Recife"
    },
    {
      "callsign": "GLO2034",
      "numero_voo": "2034",
      "airline_icao": "GLO",
      "airline": "GOL",
      "equipamento_icao": "B38M",
      "equipamento": "Boeing 737 MAX 8",
      "assentos": "186",
      "etapa": "1",
      "tipo_operacao": "Domestico",
      "tipo_servico": "REGULAR DE PASSAGEIROS DOMÉSTICA",
      "origem_icao": "SBGL",
      "destino_icao": "SBEG",
      "partida_iso": "2026-05-19T22:35:00-03:00",
      "chegada_iso": "2026-05-20T02:40:00-03:00",
      "partida_brt": "22:35",
      "chegada_brt": "02:40",
      "status": "programado",
      "fonte": "SIROS/ANAC",
      "rota": "SBGL",
      "rota_nome": "Rio de Janeiro / Galeao"
    },
    {
      "callsign": "AZU4451",
      "numero_voo": "4451",
      "airline_icao": "AZU",
      "airline": "Azul",
      "equipamento_icao": "A21N",
      "equipamento": "Airbus A321neo",
      "assentos": "214",
      "etapa": "1",
      "tipo_operacao": "Domestico",
      "tipo_servico": "REGULAR DE PASSAGEIROS DOMÉSTICA",
      "origem_icao": "SBKP",
      "destino_icao": "SBEG",
      "partida_iso": "2026-05-19T22:55:00-03:00",
      "chegada_iso": "2026-05-20T02:40:00-03:00",
      "partida_brt": "22:55",
      "chegada_brt": "02:40",
      "status": "programado",
      "fonte": "SIROS/ANAC",
      "rota": "SBKP",
      "rota_nome": "Campinas / Viracopos"
    },
    {
      "callsign": "TAM4545",
      "numero_voo": "4545",
      "airline_icao": "TAM",
      "airline": "LATAM",
      "equipamento_icao": "A321",
      "equipamento": "Airbus A321",
      "assentos": "224",
      "etapa": "1",
      "tipo_operacao": "Domestico",
      "tipo_servico": "REGULAR DE PASSAGEIROS DOMÉSTICA",
      "origem_icao": "SBGR",
      "destino_icao": "SBEG",
      "partida_iso": "2026-05-19T23:30:00-03:00",
      "chegada_iso": "2026-05-20T03:25:00-03:00",
      "partida_brt": "23:30",
      "chegada_brt": "03:25",
      "status": "programado",
      "fonte": "SIROS/ANAC",
      "rota": "SBGR",
      "rota_nome": "Sao Paulo / Guarulhos"
    },
    {
      "callsign": "CMP141",
      "numero_voo": "141",
      "airline_icao": "CMP",
      "airline": "Copa Airlines",
      "equipamento_icao": "B738",
      "equipamento": "Boeing 737-800",
      "assentos": "160",
      "etapa": "1",
      "tipo_operacao": "Internacional",
      "tipo_servico": "REGULAR DE PASSAGEIROS INTERNACIONAL",
      "origem_icao": "MPTO",
      "destino_icao": "SBEG",
      "partida_iso": "2026-05-19T23:35:00-03:00",
      "chegada_iso": "2026-05-20T03:30:00-03:00",
      "partida_brt": "23:35",
      "chegada_brt": "03:30",
      "status": "programado",
      "fonte": "SIROS/ANAC",
      "rota": "MPTO",
      "rota_nome": "MPTO"
    },
    {
      "callsign": "GLO1785",
      "numero_voo": "1785",
      "airline_icao": "GLO",
      "airline": "GOL",
      "equipamento_icao": "B38M",
      "equipamento": "Boeing 737 MAX 8",
      "assentos": "186",
      "etapa": "1",
      "tipo_operacao": "Domestico",
      "tipo_servico": "REGULAR DE PASSAGEIROS DOMÉSTICA",
      "origem_icao": "SBRB",
      "destino_icao": "SBEG",
      "partida_iso": "2026-05-20T01:50:00-03:00",
      "chegada_iso": "2026-05-20T03:45:00-03:00",
      "partida_brt": "01:50",
      "chegada_brt": "03:45",
      "status": "programado",
      "fonte": "SIROS/ANAC",
      "rota": "SBRB",
      "rota_nome": "Rio Branco"
    },
    {
      "callsign": "GTI9004",
      "numero_voo": "9004",
      "airline_icao": "GTI",
      "airline": "GTI",
      "equipamento_icao": "B763",
      "equipamento": "Boeing 767-300",
      "assentos": "0",
      "etapa": "1",
      "tipo_operacao": "Internacional",
      "tipo_servico": "REGULAR DE CARGA INTERNACIONAL",
      "origem_icao": "KMIA",
      "destino_icao": "SBEG",
      "partida_iso": "2026-05-20T01:20:00-03:00",
      "chegada_iso": "2026-05-20T06:20:00-03:00",
      "partida_brt": "01:20",
      "chegada_brt": "06:20",
      "status": "programado",
      "fonte": "SIROS/ANAC",
      "rota": "KMIA",
      "rota_nome": "KMIA"
    },
    {
      "callsign": "AZU4862",
      "numero_voo": "4862",
      "airline_icao": "AZU",
      "airline": "Azul",
      "equipamento_icao": "A20N",
      "equipamento": "Airbus A320neo",
      "assentos": "174",
      "etapa": "1",
      "tipo_operacao": "Domestico",
      "tipo_servico": "REGULAR DE PASSAGEIROS DOMÉSTICA",
      "origem_icao": "SBBE",
      "destino_icao": "SBEG",
      "partida_iso": "2026-05-20T06:30:00-03:00",
      "chegada_iso": "2026-05-20T08:35:00-03:00",
      "partida_brt": "06:30",
      "chegada_brt": "08:35",
      "status": "programado",
      "fonte": "SIROS/ANAC",
      "rota": "SBBE",
      "rota_nome": "Belem"
    },
    {
      "callsign": "LTG6550",
      "numero_voo": "6550",
      "airline_icao": "LTG",
      "airline": "LTG",
      "equipamento_icao": "B763",
      "equipamento": "Boeing 767-300",
      "assentos": "0",
      "etapa": "1",
      "tipo_operacao": "Domestico",
      "tipo_servico": "REGULAR DE CARGA DOMÉSTICA",
      "origem_icao": "SBGR",
      "destino_icao": "SBEG",
      "partida_iso": "2026-05-20T05:00:00-03:00",
      "chegada_iso": "2026-05-20T08:50:00-03:00",
      "partida_brt": "05:00",
      "chegada_brt": "08:50",
      "status": "programado",
      "fonte": "SIROS/ANAC",
      "rota": "SBGR",
      "rota_nome": "Sao Paulo / Guarulhos"
    },
    {
      "callsign": "AZU4066",
      "numero_voo": "4066",
      "airline_icao": "AZU",
      "airline": "Azul",
      "equipamento_icao": "A20N",
      "equipamento": "Airbus A320neo",
      "assentos": "174",
      "etapa": "1",
      "tipo_operacao": "Domestico",
      "tipo_servico": "REGULAR DE PASSAGEIROS DOMÉSTICA",
      "origem_icao": "SBCF",
      "destino_icao": "SBEG",
      "partida_iso": "2026-05-20T08:05:00-03:00",
      "chegada_iso": "2026-05-20T11:40:00-03:00",
      "partida_brt": "08:05",
      "chegada_brt": "11:40",
      "status": "programado",
      "fonte": "SIROS/ANAC",
      "rota": "SBCF",
      "rota_nome": "Belo Horizonte / Confins"
    },
    {
      "callsign": "GLO1782",
      "numero_voo": "1782",
      "airline_icao": "GLO",
      "airline": "GOL",
      "equipamento_icao": "B38M",
      "equipamento": "Boeing 737 MAX 8",
      "assentos": "186",
      "etapa": "1",
      "tipo_operacao": "Domestico",
      "tipo_servico": "REGULAR DE PASSAGEIROS DOMÉSTICA",
      "origem_icao": "SBBR",
      "destino_icao": "SBEG",
      "partida_iso": "2026-05-20T08:45:00-03:00",
      "chegada_iso": "2026-05-20T11:45:00-03:00",
      "partida_brt": "08:45",
      "chegada_brt": "11:45",
      "status": "programado",
      "fonte": "SIROS/ANAC",
      "rota": "SBBR",
      "rota_nome": "Brasilia"
    },
    {
      "callsign": "TAM3560",
      "numero_voo": "3560",
      "airline_icao": "TAM",
      "airline": "LATAM",
      "equipamento_icao": "A321",
      "equipamento": "Airbus A321",
      "assentos": "224",
      "etapa": "1",
      "tipo_operacao": "Domestico",
      "tipo_servico": "REGULAR DE PASSAGEIROS DOMÉSTICA",
      "origem_icao": "SBGR",
      "destino_icao": "SBEG",
      "partida_iso": "2026-05-20T07:50:00-03:00",
      "chegada_iso": "2026-05-20T11:50:00-03:00",
      "partida_brt": "07:50",
      "chegada_brt": "11:50",
      "status": "programado",
      "fonte": "SIROS/ANAC",
      "rota": "SBGR",
      "rota_nome": "Sao Paulo / Guarulhos"
    },
    {
      "callsign": "BPC6301",
      "numero_voo": "6301",
      "airline_icao": "BPC",
      "airline": "BPC",
      "equipamento_icao": "B734",
      "equipamento": "B734",
      "assentos": "0",
      "etapa": "1",
      "tipo_operacao": "Domestico",
      "tipo_servico": "NÃO REGULAR DE CARGA DOMÉSTICA",
      "origem_icao": "SBKP",
      "destino_icao": "SBEG",
      "partida_iso": "2026-05-20T08:00:00-03:00",
      "chegada_iso": "2026-05-20T12:00:00-03:00",
      "partida_brt": "08:00",
      "chegada_brt": "12:00",
      "status": "programado",
      "fonte": "SIROS/ANAC",
      "rota": "SBKP",
      "rota_nome": "Campinas / Viracopos"
    },
    {
      "callsign": "SID9305",
      "numero_voo": "9305",
      "airline_icao": "SID",
      "airline": "SID",
      "equipamento_icao": "B734",
      "equipamento": "B734",
      "assentos": "0",
      "etapa": "2",
      "tipo_operacao": "Domestico",
      "tipo_servico": "NÃO REGULAR DE CARGA DOMÉSTICA",
      "origem_icao": "SBBR",
      "destino_icao": "SBEG",
      "partida_iso": "2026-05-20T09:10:00-03:00",
      "chegada_iso": "2026-05-20T12:05:00-03:00",
      "partida_brt": "09:10",
      "chegada_brt": "12:05",
      "status": "programado",
      "fonte": "SIROS/ANAC",
      "rota": "SBBR",
      "rota_nome": "Brasilia"
    },
    {
      "callsign": "AZU2943",
      "numero_voo": "2943",
      "airline_icao": "AZU",
      "airline": "Azul",
      "equipamento_icao": "A20N",
      "equipamento": "Airbus A320neo",
      "assentos": "174",
      "etapa": "1",
      "tipo_operacao": "Domestico",
      "tipo_servico": "REGULAR DE PASSAGEIROS DOMÉSTICA",
      "origem_icao": "SBKP",
      "destino_icao": "SBEG",
      "partida_iso": "2026-05-20T08:25:00-03:00",
      "chegada_iso": "2026-05-20T12:10:00-03:00",
      "partida_brt": "08:25",
      "chegada_brt": "12:10",
      "status": "programado",
      "fonte": "SIROS/ANAC",
      "rota": "SBKP",
      "rota_nome": "Campinas / Viracopos"
    },
    {
      "callsign": "TAM3748",
      "numero_voo": "3748",
      "airline_icao": "TAM",
      "airline": "LATAM",
      "equipamento_icao": "A320",
      "equipamento": "Airbus A320",
      "assentos": "180",
      "etapa": "1",
      "tipo_operacao": "Domestico",
      "tipo_servico": "REGULAR DE PASSAGEIROS DOMÉSTICA",
      "origem_icao": "SBBR",
      "destino_icao": "SBEG",
      "partida_iso": "2026-05-20T09:10:00-03:00",
      "chegada_iso": "2026-05-20T12:10:00-03:00",
      "partida_brt": "09:10",
      "chegada_brt": "12:10",
      "status": "programado",
      "fonte": "SIROS/ANAC",
      "rota": "SBBR",
      "rota_nome": "Brasilia"
    },
    {
      "callsign": "AZU4245",
      "numero_voo": "4245",
      "airline_icao": "AZU",
      "airline": "Azul",
      "equipamento_icao": "AT76",
      "equipamento": "ATR 72",
      "assentos": "70",
      "etapa": "1",
      "tipo_operacao": "Domestico",
      "tipo_servico": "REGULAR DE PASSAGEIROS DOMÉSTICA",
      "origem_icao": "SWPI",
      "destino_icao": "SBEG",
      "partida_iso": "2026-05-20T11:10:00-03:00",
      "chegada_iso": "2026-05-20T12:20:00-03:00",
      "partida_brt": "11:10",
      "chegada_brt": "12:20",
      "status": "programado",
      "fonte": "SIROS/ANAC",
      "rota": "SWPI",
      "rota_nome": "SWPI"
    },
    {
      "callsign": "AZU9586",
      "numero_voo": "9586",
      "airline_icao": "AZU",
      "airline": "Azul",
      "equipamento_icao": "AT76",
      "equipamento": "ATR 72",
      "assentos": "70",
      "etapa": "1",
      "tipo_operacao": "Domestico",
      "tipo_servico": "NÃO REGULAR DE PASSAGEIROS DOMÉSTICA",
      "origem_icao": "SBUY",
      "destino_icao": "SBEG",
      "partida_iso": "2026-05-20T11:45:00-03:00",
      "chegada_iso": "2026-05-20T13:30:00-03:00",
      "partida_brt": "11:45",
      "chegada_brt": "13:30",
      "status": "programado",
      "fonte": "SIROS/ANAC",
      "rota": "SBUY",
      "rota_nome": "SBUY"
    },
    {
      "callsign": "GLO1783",
      "numero_voo": "1783",
      "airline_icao": "GLO",
      "airline": "GOL",
      "equipamento_icao": "B38M",
      "equipamento": "Boeing 737 MAX 8",
      "assentos": "186",
      "etapa": "1",
      "tipo_operacao": "Domestico",
      "tipo_servico": "REGULAR DE PASSAGEIROS DOMÉSTICA",
      "origem_icao": "SBSN",
      "destino_icao": "SBEG",
      "partida_iso": "2026-05-20T14:15:00-03:00",
      "chegada_iso": "2026-05-20T15:35:00-03:00",
      "partida_brt": "14:15",
      "chegada_brt": "15:35",
      "status": "programado",
      "fonte": "SIROS/ANAC",
      "rota": "SBSN",
      "rota_nome": "Santarem"
    },
    {
      "callsign": "AZU2060",
      "numero_voo": "2060",
      "airline_icao": "AZU",
      "airline": "Azul",
      "equipamento_icao": "A21N",
      "equipamento": "Airbus A321neo",
      "assentos": "0",
      "etapa": "1",
      "tipo_operacao": "Domestico",
      "tipo_servico": "REGULAR DE CARGA DOMÉSTICA",
      "origem_icao": "SBKP",
      "destino_icao": "SBEG",
      "partida_iso": "2026-05-20T12:10:00-03:00",
      "chegada_iso": "2026-05-20T15:55:00-03:00",
      "partida_brt": "12:10",
      "chegada_brt": "15:55",
      "status": "programado",
      "fonte": "SIROS/ANAC",
      "rota": "SBKP",
      "rota_nome": "Campinas / Viracopos"
    },
    {
      "callsign": "TPA4057",
      "numero_voo": "4057",
      "airline_icao": "TPA",
      "airline": "TPA",
      "equipamento_icao": "A332",
      "equipamento": "Airbus A330-200",
      "assentos": "0",
      "etapa": "1",
      "tipo_operacao": "Internacional",
      "tipo_servico": "REGULAR DE CARGA INTERNACIONAL",
      "origem_icao": "KMIA",
      "destino_icao": "SBEG",
      "partida_iso": "2026-05-20T11:00:00-03:00",
      "chegada_iso": "2026-05-20T16:10:00-03:00",
      "partida_brt": "11:00",
      "chegada_brt": "16:10",
      "status": "programado",
      "fonte": "SIROS/ANAC",
      "rota": "KMIA",
      "rota_nome": "KMIA"
    },
    {
      "callsign": "AZU4184",
      "numero_voo": "4184",
      "airline_icao": "AZU",
      "airline": "Azul",
      "equipamento_icao": "E195",
      "equipamento": "Embraer E195",
      "assentos": "118",
      "etapa": "1",
      "tipo_operacao": "Domestico",
      "tipo_servico": "REGULAR DE PASSAGEIROS DOMÉSTICA",
      "origem_icao": "SBTF",
      "destino_icao": "SBEG",
      "partida_iso": "2026-05-20T15:10:00-03:00",
      "chegada_iso": "2026-05-20T16:15:00-03:00",
      "partida_brt": "15:10",
      "chegada_brt": "16:15",
      "status": "programado",
      "fonte": "SIROS/ANAC",
      "rota": "SBTF",
      "rota_nome": "SBTF"
    },
    {
      "callsign": "TAM3296",
      "numero_voo": "3296",
      "airline_icao": "TAM",
      "airline": "LATAM",
      "equipamento_icao": "A321",
      "equipamento": "Airbus A321",
      "assentos": "224",
      "etapa": "1",
      "tipo_operacao": "Domestico",
      "tipo_servico": "REGULAR DE PASSAGEIROS DOMÉSTICA",
      "origem_icao": "SBGR",
      "destino_icao": "SBEG",
      "partida_iso": "2026-05-20T12:35:00-03:00",
      "chegada_iso": "2026-05-20T16:35:00-03:00",
      "partida_brt": "12:35",
      "chegada_brt": "16:35",
      "status": "programado",
      "fonte": "SIROS/ANAC",
      "rota": "SBGR",
      "rota_nome": "Sao Paulo / Guarulhos"
    },
    {
      "callsign": "AZU4013",
      "numero_voo": "4013",
      "airline_icao": "AZU",
      "airline": "Azul",
      "equipamento_icao": "A20N",
      "equipamento": "Airbus A320neo",
      "assentos": "174",
      "etapa": "1",
      "tipo_operacao": "Domestico",
      "tipo_servico": "REGULAR DE PASSAGEIROS DOMÉSTICA",
      "origem_icao": "SBBV",
      "destino_icao": "SBEG",
      "partida_iso": "2026-05-20T15:15:00-03:00",
      "chegada_iso": "2026-05-20T16:35:00-03:00",
      "partida_brt": "15:15",
      "chegada_brt": "16:35",
      "status": "programado",
      "fonte": "SIROS/ANAC",
      "rota": "SBBV",
      "rota_nome": "Boa Vista"
    },
    {
      "callsign": "AZU4056",
      "numero_voo": "4056",
      "airline_icao": "AZU",
      "airline": "Azul",
      "equipamento_icao": "A20N",
      "equipamento": "Airbus A320neo",
      "assentos": "174",
      "etapa": "1",
      "tipo_operacao": "Domestico",
      "tipo_servico": "REGULAR DE PASSAGEIROS DOMÉSTICA",
      "origem_icao": "SBKP",
      "destino_icao": "SBEG",
      "partida_iso": "2026-05-20T13:00:00-03:00",
      "chegada_iso": "2026-05-20T16:50:00-03:00",
      "partida_brt": "13:00",
      "chegada_brt": "16:50",
      "status": "programado",
      "fonte": "SIROS/ANAC",
      "rota": "SBKP",
      "rota_nome": "Campinas / Viracopos"
    },
    {
      "callsign": "ACN5314",
      "numero_voo": "5314",
      "airline_icao": "ACN",
      "airline": "ACN",
      "equipamento_icao": "C208",
      "equipamento": "C208",
      "assentos": "9",
      "etapa": "1",
      "tipo_operacao": "Domestico",
      "tipo_servico": "REGULAR DE PASSAGEIROS DOMÉSTICA",
      "origem_icao": "SBMY",
      "destino_icao": "SBEG",
      "partida_iso": "2026-05-20T15:30:00-03:00",
      "chegada_iso": "2026-05-20T17:10:00-03:00",
      "partida_brt": "15:30",
      "chegada_brt": "17:10",
      "status": "programado",
      "fonte": "SIROS/ANAC",
      "rota": "SBMY",
      "rota_nome": "SBMY"
    },
    {
      "callsign": "TAP51",
      "numero_voo": "51",
      "airline_icao": "TAP",
      "airline": "TAP Portugal",
      "equipamento_icao": "A21N",
      "equipamento": "Airbus A321neo",
      "assentos": "168",
      "etapa": "2",
      "tipo_operacao": "Internacional",
      "tipo_servico": "REGULAR DE PASSAGEIROS INTERNACIONAL",
      "origem_icao": "SBBE",
      "destino_icao": "SBEG",
      "partida_iso": "2026-05-20T15:35:00-03:00",
      "chegada_iso": "2026-05-20T17:45:00-03:00",
      "partida_brt": "15:35",
      "chegada_brt": "17:45",
      "status": "programado",
      "fonte": "SIROS/ANAC",
      "rota": "SBBE",
      "rota_nome": "Belem"
    },
    {
      "callsign": "TAM3525",
      "numero_voo": "3525",
      "airline_icao": "TAM",
      "airline": "LATAM",
      "equipamento_icao": "A321",
      "equipamento": "Airbus A321",
      "assentos": "224",
      "etapa": "1",
      "tipo_operacao": "Domestico",
      "tipo_servico": "REGULAR DE PASSAGEIROS DOMÉSTICA",
      "origem_icao": "SBFZ",
      "destino_icao": "SBEG",
      "partida_iso": "2026-05-20T14:20:00-03:00",
      "chegada_iso": "2026-05-20T17:45:00-03:00",
      "partida_brt": "14:20",
      "chegada_brt": "17:45",
      "status": "programado",
      "fonte": "SIROS/ANAC",
      "rota": "SBFZ",
      "rota_nome": "Fortaleza"
    },
    {
      "callsign": "LTG6560",
      "numero_voo": "6560",
      "airline_icao": "LTG",
      "airline": "LTG",
      "equipamento_icao": "B763",
      "equipamento": "Boeing 767-300",
      "assentos": "0",
      "etapa": "1",
      "tipo_operacao": "Domestico",
      "tipo_servico": "REGULAR DE CARGA DOMÉSTICA",
      "origem_icao": "SBGR",
      "destino_icao": "SBEG",
      "partida_iso": "2026-05-20T14:55:00-03:00",
      "chegada_iso": "2026-05-20T18:45:00-03:00",
      "partida_brt": "14:55",
      "chegada_brt": "18:45",
      "status": "programado",
      "fonte": "SIROS/ANAC",
      "rota": "SBGR",
      "rota_nome": "Sao Paulo / Guarulhos"
    },
    {
      "callsign": "AZU4418",
      "numero_voo": "4418",
      "airline_icao": "AZU",
      "airline": "Azul",
      "equipamento_icao": "AT76",
      "equipamento": "ATR 72",
      "assentos": "70",
      "etapa": "3",
      "tipo_operacao": "Domestico",
      "tipo_servico": "REGULAR DE PASSAGEIROS DOMÉSTICA",
      "origem_icao": "SBTB",
      "destino_icao": "SBEG",
      "partida_iso": "2026-05-20T17:50:00-03:00",
      "chegada_iso": "2026-05-20T19:10:00-03:00",
      "partida_brt": "17:50",
      "chegada_brt": "19:10",
      "status": "programado",
      "fonte": "SIROS/ANAC",
      "rota": "SBTB",
      "rota_nome": "SBTB"
    },
    {
      "callsign": "AZU4545",
      "numero_voo": "4545",
      "airline_icao": "AZU",
      "airline": "Azul",
      "equipamento_icao": "A20N",
      "equipamento": "Airbus A320neo",
      "assentos": "174",
      "etapa": "1",
      "tipo_operacao": "Domestico",
      "tipo_servico": "REGULAR DE PASSAGEIROS DOMÉSTICA",
      "origem_icao": "SBBE",
      "destino_icao": "SBEG",
      "partida_iso": "2026-05-20T17:55:00-03:00",
      "chegada_iso": "2026-05-20T19:55:00-03:00",
      "partida_brt": "17:55",
      "chegada_brt": "19:55",
      "status": "programado",
      "fonte": "SIROS/ANAC",
      "rota": "SBBE",
      "rota_nome": "Belem"
    },
    {
      "callsign": "GLO9628",
      "numero_voo": "9628",
      "airline_icao": "GLO",
      "airline": "GOL",
      "equipamento_icao": "B738",
      "equipamento": "Boeing 737-800",
      "assentos": "0",
      "etapa": "1",
      "tipo_operacao": "Domestico",
      "tipo_servico": "REGULAR DE CARGA DOMÉSTICA",
      "origem_icao": "SBGR",
      "destino_icao": "SBEG",
      "partida_iso": "2026-05-20T16:40:00-03:00",
      "chegada_iso": "2026-05-20T20:35:00-03:00",
      "partida_brt": "16:40",
      "chegada_brt": "20:35",
      "status": "programado",
      "fonte": "SIROS/ANAC",
      "rota": "SBGR",
      "rota_nome": "Sao Paulo / Guarulhos"
    },
    {
      "callsign": "AZU9588",
      "numero_voo": "9588",
      "airline_icao": "AZU",
      "airline": "Azul",
      "equipamento_icao": "AT76",
      "equipamento": "ATR 72",
      "assentos": "70",
      "etapa": "1",
      "tipo_operacao": "Domestico",
      "tipo_servico": "NÃO REGULAR DE PASSAGEIROS DOMÉSTICA",
      "origem_icao": "SBUY",
      "destino_icao": "SBEG",
      "partida_iso": "2026-05-20T19:00:00-03:00",
      "chegada_iso": "2026-05-20T20:45:00-03:00",
      "partida_brt": "19:00",
      "chegada_brt": "20:45",
      "status": "programado",
      "fonte": "SIROS/ANAC",
      "rota": "SBUY",
      "rota_nome": "SBUY"
    },
    {
      "callsign": "AZU4186",
      "numero_voo": "4186",
      "airline_icao": "AZU",
      "airline": "Azul",
      "equipamento_icao": "E195",
      "equipamento": "Embraer E195",
      "assentos": "118",
      "etapa": "1",
      "tipo_operacao": "Domestico",
      "tipo_servico": "REGULAR DE PASSAGEIROS DOMÉSTICA",
      "origem_icao": "SBTT",
      "destino_icao": "SBEG",
      "partida_iso": "2026-05-20T19:20:00-03:00",
      "chegada_iso": "2026-05-20T21:10:00-03:00",
      "partida_brt": "19:20",
      "chegada_brt": "21:10",
      "status": "programado",
      "fonte": "SIROS/ANAC",
      "rota": "SBTT",
      "rota_nome": "SBTT"
    },
    {
      "callsign": "GLO1542",
      "numero_voo": "1542",
      "airline_icao": "GLO",
      "airline": "GOL",
      "equipamento_icao": "B738",
      "equipamento": "Boeing 737-800",
      "assentos": "186",
      "etapa": "1",
      "tipo_operacao": "Domestico",
      "tipo_servico": "REGULAR DE PASSAGEIROS DOMÉSTICA",
      "origem_icao": "SBGR",
      "destino_icao": "SBEG",
      "partida_iso": "2026-05-20T18:30:00-03:00",
      "chegada_iso": "2026-05-20T22:25:00-03:00",
      "partida_brt": "18:30",
      "chegada_brt": "22:25",
      "status": "programado",
      "fonte": "SIROS/ANAC",
      "rota": "SBGR",
      "rota_nome": "Sao Paulo / Guarulhos"
    },
    {
      "callsign": "GLO9610",
      "numero_voo": "9610",
      "airline_icao": "GLO",
      "airline": "GOL",
      "equipamento_icao": "B738",
      "equipamento": "Boeing 737-800",
      "assentos": "0",
      "etapa": "2",
      "tipo_operacao": "Domestico",
      "tipo_servico": "REGULAR DE CARGA DOMÉSTICA",
      "origem_icao": "SBBE",
      "destino_icao": "SBEG",
      "partida_iso": "2026-05-20T20:35:00-03:00",
      "chegada_iso": "2026-05-20T22:40:00-03:00",
      "partida_brt": "20:35",
      "chegada_brt": "22:40",
      "status": "programado",
      "fonte": "SIROS/ANAC",
      "rota": "SBBE",
      "rota_nome": "Belem"
    },
    {
      "callsign": "TAM3562",
      "numero_voo": "3562",
      "airline_icao": "TAM",
      "airline": "LATAM",
      "equipamento_icao": "A321",
      "equipamento": "Airbus A321",
      "assentos": "224",
      "etapa": "1",
      "tipo_operacao": "Domestico",
      "tipo_servico": "REGULAR DE PASSAGEIROS DOMÉSTICA",
      "origem_icao": "SBGR",
      "destino_icao": "SBEG",
      "partida_iso": "2026-05-20T18:50:00-03:00",
      "chegada_iso": "2026-05-20T22:45:00-03:00",
      "partida_brt": "18:50",
      "chegada_brt": "22:45",
      "status": "programado",
      "fonte": "SIROS/ANAC",
      "rota": "SBGR",
      "rota_nome": "Sao Paulo / Guarulhos"
    },
    {
      "callsign": "GLO1784",
      "numero_voo": "1784",
      "airline_icao": "GLO",
      "airline": "GOL",
      "equipamento_icao": "B38M",
      "equipamento": "Boeing 737 MAX 8",
      "assentos": "186",
      "etapa": "1",
      "tipo_operacao": "Domestico",
      "tipo_servico": "REGULAR DE PASSAGEIROS DOMÉSTICA",
      "origem_icao": "SBBR",
      "destino_icao": "SBEG",
      "partida_iso": "2026-05-20T20:55:00-03:00",
      "chegada_iso": "2026-05-20T23:50:00-03:00",
      "partida_brt": "20:55",
      "chegada_brt": "23:50",
      "status": "programado",
      "fonte": "SIROS/ANAC",
      "rota": "SBBR",
      "rota_nome": "Brasilia"
    },
    {
      "callsign": "TAM3890",
      "numero_voo": "3890",
      "airline_icao": "TAM",
      "airline": "LATAM",
      "equipamento_icao": "A320",
      "equipamento": "Airbus A320",
      "assentos": "180",
      "etapa": "1",
      "tipo_operacao": "Domestico",
      "tipo_servico": "REGULAR DE PASSAGEIROS DOMÉSTICA",
      "origem_icao": "SBGL",
      "destino_icao": "SBEG",
      "partida_iso": "2026-05-20T20:50:00-03:00",
      "chegada_iso": "2026-05-21T01:05:00-03:00",
      "partida_brt": "20:50",
      "chegada_brt": "01:05",
      "status": "programado",
      "fonte": "SIROS/ANAC",
      "rota": "SBGL",
      "rota_nome": "Rio de Janeiro / Galeao"
    },
    {
      "callsign": "GLO1756",
      "numero_voo": "1756",
      "airline_icao": "GLO",
      "airline": "GOL",
      "equipamento_icao": "B38M",
      "equipamento": "Boeing 737 MAX 8",
      "assentos": "186",
      "etapa": "2",
      "tipo_operacao": "Domestico",
      "tipo_servico": "REGULAR DE PASSAGEIROS DOMÉSTICA",
      "origem_icao": "SBPV",
      "destino_icao": "SBEG",
      "partida_iso": "2026-05-21T00:30:00-03:00",
      "chegada_iso": "2026-05-21T01:55:00-03:00",
      "partida_brt": "00:30",
      "chegada_brt": "01:55",
      "status": "programado",
      "fonte": "SIROS/ANAC",
      "rota": "SBPV",
      "rota_nome": "Porto Velho"
    }
  ],
  "departures": [
    {
      "callsign": "AZU6100",
      "numero_voo": "6100",
      "airline_icao": "AZU",
      "airline": "Azul",
      "equipamento_icao": "AT76",
      "equipamento": "ATR 72",
      "assentos": "70",
      "etapa": "1",
      "tipo_operacao": "Domestico",
      "tipo_servico": "REGULAR DE PASSAGEIROS DOMÉSTICA",
      "origem_icao": "SBEG",
      "destino_icao": "SBSN",
      "partida_iso": "2026-05-19T22:25:00-03:00",
      "chegada_iso": "2026-05-20T00:05:00-03:00",
      "partida_brt": "22:25",
      "chegada_brt": "00:05",
      "status": "programado",
      "fonte": "SIROS/ANAC",
      "rota": "SBSN",
      "rota_nome": "Santarem"
    },
    {
      "callsign": "TAM3188",
      "numero_voo": "3188",
      "airline_icao": "TAM",
      "airline": "LATAM",
      "equipamento_icao": "A320",
      "equipamento": "Airbus A320",
      "assentos": "180",
      "etapa": "1",
      "tipo_operacao": "Domestico",
      "tipo_servico": "REGULAR DE PASSAGEIROS DOMÉSTICA",
      "origem_icao": "SBEG",
      "destino_icao": "SBBE",
      "partida_iso": "2026-05-19T23:40:00-03:00",
      "chegada_iso": "2026-05-20T01:50:00-03:00",
      "partida_brt": "23:40",
      "chegada_brt": "01:50",
      "status": "programado",
      "fonte": "SIROS/ANAC",
      "rota": "SBBE",
      "rota_nome": "Belem"
    },
    {
      "callsign": "LTG8410",
      "numero_voo": "8410",
      "airline_icao": "LTG",
      "airline": "LTG",
      "equipamento_icao": "B763",
      "equipamento": "Boeing 767-300",
      "assentos": "0",
      "etapa": "1",
      "tipo_operacao": "Internacional",
      "tipo_servico": "REGULAR DE CARGA INTERNACIONAL",
      "origem_icao": "SBEG",
      "destino_icao": "SEQM",
      "partida_iso": "2026-05-19T23:50:00-03:00",
      "chegada_iso": "2026-05-20T03:00:00-03:00",
      "partida_brt": "23:50",
      "chegada_brt": "03:00",
      "status": "programado",
      "fonte": "SIROS/ANAC",
      "rota": "SEQM",
      "rota_nome": "SEQM"
    },
    {
      "callsign": "GLO9629",
      "numero_voo": "9629",
      "airline_icao": "GLO",
      "airline": "GOL",
      "equipamento_icao": "B738",
      "equipamento": "Boeing 737-800",
      "assentos": "0",
      "etapa": "1",
      "tipo_operacao": "Domestico",
      "tipo_servico": "REGULAR DE CARGA DOMÉSTICA",
      "origem_icao": "SBEG",
      "destino_icao": "SBGR",
      "partida_iso": "2026-05-20T00:00:00-03:00",
      "chegada_iso": "2026-05-20T03:45:00-03:00",
      "partida_brt": "00:00",
      "chegada_brt": "03:45",
      "status": "programado",
      "fonte": "SIROS/ANAC",
      "rota": "SBGR",
      "rota_nome": "Sao Paulo / Guarulhos"
    },
    {
      "callsign": "AZU2054",
      "numero_voo": "2054",
      "airline_icao": "AZU",
      "airline": "Azul",
      "equipamento_icao": "A21N",
      "equipamento": "Airbus A321neo",
      "assentos": "0",
      "etapa": "1",
      "tipo_operacao": "Domestico",
      "tipo_servico": "REGULAR DE CARGA DOMÉSTICA",
      "origem_icao": "SBEG",
      "destino_icao": "SBKP",
      "partida_iso": "2026-05-20T01:20:00-03:00",
      "chegada_iso": "2026-05-20T05:00:00-03:00",
      "partida_brt": "01:20",
      "chegada_brt": "05:00",
      "status": "programado",
      "fonte": "SIROS/ANAC",
      "rota": "SBKP",
      "rota_nome": "Campinas / Viracopos"
    },
    {
      "callsign": "TAM3565",
      "numero_voo": "3565",
      "airline_icao": "TAM",
      "airline": "LATAM",
      "equipamento_icao": "A320",
      "equipamento": "Airbus A320",
      "assentos": "180",
      "etapa": "1",
      "tipo_operacao": "Domestico",
      "tipo_servico": "REGULAR DE PASSAGEIROS DOMÉSTICA",
      "origem_icao": "SBEG",
      "destino_icao": "SBGR",
      "partida_iso": "2026-05-20T02:15:00-03:00",
      "chegada_iso": "2026-05-20T06:10:00-03:00",
      "partida_brt": "02:15",
      "chegada_brt": "06:10",
      "status": "programado",
      "fonte": "SIROS/ANAC",
      "rota": "SBGR",
      "rota_nome": "Sao Paulo / Guarulhos"
    },
    {
      "callsign": "GLO1757",
      "numero_voo": "1757",
      "airline_icao": "GLO",
      "airline": "GOL",
      "equipamento_icao": "B38M",
      "equipamento": "Boeing 737 MAX 8",
      "assentos": "186",
      "etapa": "1",
      "tipo_operacao": "Domestico",
      "tipo_servico": "REGULAR DE PASSAGEIROS DOMÉSTICA",
      "origem_icao": "SBEG",
      "destino_icao": "SBPV",
      "partida_iso": "2026-05-20T02:40:00-03:00",
      "chegada_iso": "2026-05-20T04:10:00-03:00",
      "partida_brt": "02:40",
      "chegada_brt": "04:10",
      "status": "programado",
      "fonte": "SIROS/ANAC",
      "rota": "SBPV",
      "rota_nome": "Porto Velho"
    },
    {
      "callsign": "GLO1545",
      "numero_voo": "1545",
      "airline_icao": "GLO",
      "airline": "GOL",
      "equipamento_icao": "B38M",
      "equipamento": "Boeing 737 MAX 8",
      "assentos": "186",
      "etapa": "1",
      "tipo_operacao": "Domestico",
      "tipo_servico": "REGULAR DE PASSAGEIROS DOMÉSTICA",
      "origem_icao": "SBEG",
      "destino_icao": "SBGR",
      "partida_iso": "2026-05-20T03:20:00-03:00",
      "chegada_iso": "2026-05-20T07:25:00-03:00",
      "partida_brt": "03:20",
      "chegada_brt": "07:25",
      "status": "programado",
      "fonte": "SIROS/ANAC",
      "rota": "SBGR",
      "rota_nome": "Sao Paulo / Guarulhos"
    },
    {
      "callsign": "GLO2035",
      "numero_voo": "2035",
      "airline_icao": "GLO",
      "airline": "GOL",
      "equipamento_icao": "B38M",
      "equipamento": "Boeing 737 MAX 8",
      "assentos": "186",
      "etapa": "1",
      "tipo_operacao": "Domestico",
      "tipo_servico": "REGULAR DE PASSAGEIROS DOMÉSTICA",
      "origem_icao": "SBEG",
      "destino_icao": "SBGL",
      "partida_iso": "2026-05-20T03:30:00-03:00",
      "chegada_iso": "2026-05-20T07:30:00-03:00",
      "partida_brt": "03:30",
      "chegada_brt": "07:30",
      "status": "programado",
      "fonte": "SIROS/ANAC",
      "rota": "SBGL",
      "rota_nome": "Rio de Janeiro / Galeao"
    },
    {
      "callsign": "AZU4383",
      "numero_voo": "4383",
      "airline_icao": "AZU",
      "airline": "Azul",
      "equipamento_icao": "A21N",
      "equipamento": "Airbus A321neo",
      "assentos": "214",
      "etapa": "1",
      "tipo_operacao": "Domestico",
      "tipo_servico": "REGULAR DE PASSAGEIROS DOMÉSTICA",
      "origem_icao": "SBEG",
      "destino_icao": "SBKP",
      "partida_iso": "2026-05-20T03:30:00-03:00",
      "chegada_iso": "2026-05-20T07:10:00-03:00",
      "partida_brt": "03:30",
      "chegada_brt": "07:10",
      "status": "programado",
      "fonte": "SIROS/ANAC",
      "rota": "SBKP",
      "rota_nome": "Campinas / Viracopos"
    },
    {
      "callsign": "AZU2601",
      "numero_voo": "2601",
      "airline_icao": "AZU",
      "airline": "Azul",
      "equipamento_icao": "A21N",
      "equipamento": "Airbus A321neo",
      "assentos": "214",
      "etapa": "1",
      "tipo_operacao": "Domestico",
      "tipo_servico": "REGULAR DE PASSAGEIROS DOMÉSTICA",
      "origem_icao": "SBEG",
      "destino_icao": "SBRF",
      "partida_iso": "2026-05-20T03:35:00-03:00",
      "chegada_iso": "2026-05-20T07:25:00-03:00",
      "partida_brt": "03:35",
      "chegada_brt": "07:25",
      "status": "programado",
      "fonte": "SIROS/ANAC",
      "rota": "SBRF",
      "rota_nome": "Recife"
    },
    {
      "callsign": "AZU2031",
      "numero_voo": "2031",
      "airline_icao": "AZU",
      "airline": "Azul",
      "equipamento_icao": "A21N",
      "equipamento": "Airbus A321neo",
      "assentos": "0",
      "etapa": "1",
      "tipo_operacao": "Domestico",
      "tipo_servico": "REGULAR DE CARGA DOMÉSTICA",
      "origem_icao": "SBEG",
      "destino_icao": "SBKP",
      "partida_iso": "2026-05-20T03:50:00-03:00",
      "chegada_iso": "2026-05-20T07:30:00-03:00",
      "partida_brt": "03:50",
      "chegada_brt": "07:30",
      "status": "programado",
      "fonte": "SIROS/ANAC",
      "rota": "SBKP",
      "rota_nome": "Campinas / Viracopos"
    },
    {
      "callsign": "TAM3747",
      "numero_voo": "3747",
      "airline_icao": "TAM",
      "airline": "LATAM",
      "equipamento_icao": "A321",
      "equipamento": "Airbus A321",
      "assentos": "224",
      "etapa": "1",
      "tipo_operacao": "Domestico",
      "tipo_servico": "REGULAR DE PASSAGEIROS DOMÉSTICA",
      "origem_icao": "SBEG",
      "destino_icao": "SBBR",
      "partida_iso": "2026-05-20T04:25:00-03:00",
      "chegada_iso": "2026-05-20T07:25:00-03:00",
      "partida_brt": "04:25",
      "chegada_brt": "07:25",
      "status": "programado",
      "fonte": "SIROS/ANAC",
      "rota": "SBBR",
      "rota_nome": "Brasilia"
    },
    {
      "callsign": "GLO1785",
      "numero_voo": "1785",
      "airline_icao": "GLO",
      "airline": "GOL",
      "equipamento_icao": "B38M",
      "equipamento": "Boeing 737 MAX 8",
      "assentos": "186",
      "etapa": "2",
      "tipo_operacao": "Domestico",
      "tipo_servico": "REGULAR DE PASSAGEIROS DOMÉSTICA",
      "origem_icao": "SBEG",
      "destino_icao": "SBBR",
      "partida_iso": "2026-05-20T04:30:00-03:00",
      "chegada_iso": "2026-05-20T07:30:00-03:00",
      "partida_brt": "04:30",
      "chegada_brt": "07:30",
      "status": "programado",
      "fonte": "SIROS/ANAC",
      "rota": "SBBR",
      "rota_nome": "Brasilia"
    },
    {
      "callsign": "CMP140",
      "numero_voo": "140",
      "airline_icao": "CMP",
      "airline": "Copa Airlines",
      "equipamento_icao": "B738",
      "equipamento": "Boeing 737-800",
      "assentos": "160",
      "etapa": "1",
      "tipo_operacao": "Internacional",
      "tipo_servico": "REGULAR DE PASSAGEIROS INTERNACIONAL",
      "origem_icao": "SBEG",
      "destino_icao": "MPTO",
      "partida_iso": "2026-05-20T04:35:00-03:00",
      "chegada_iso": "2026-05-20T08:25:00-03:00",
      "partida_brt": "04:35",
      "chegada_brt": "08:25",
      "status": "programado",
      "fonte": "SIROS/ANAC",
      "rota": "MPTO",
      "rota_nome": "MPTO"
    },
    {
      "callsign": "GTI9004",
      "numero_voo": "9004",
      "airline_icao": "GTI",
      "airline": "GTI",
      "equipamento_icao": "B763",
      "equipamento": "Boeing 767-300",
      "assentos": "0",
      "etapa": "2",
      "tipo_operacao": "Internacional",
      "tipo_servico": "REGULAR DE CARGA INTERNACIONAL",
      "origem_icao": "SBEG",
      "destino_icao": "SEQM",
      "partida_iso": "2026-05-20T08:20:00-03:00",
      "chegada_iso": "2026-05-20T11:20:00-03:00",
      "partida_brt": "08:20",
      "chegada_brt": "11:20",
      "status": "programado",
      "fonte": "SIROS/ANAC",
      "rota": "SEQM",
      "rota_nome": "SEQM"
    },
    {
      "callsign": "AZU4544",
      "numero_voo": "4544",
      "airline_icao": "AZU",
      "airline": "Azul",
      "equipamento_icao": "A20N",
      "equipamento": "Airbus A320neo",
      "assentos": "174",
      "etapa": "1",
      "tipo_operacao": "Domestico",
      "tipo_servico": "REGULAR DE PASSAGEIROS DOMÉSTICA",
      "origem_icao": "SBEG",
      "destino_icao": "SBBE",
      "partida_iso": "2026-05-20T09:15:00-03:00",
      "chegada_iso": "2026-05-20T11:20:00-03:00",
      "partida_brt": "09:15",
      "chegada_brt": "11:20",
      "status": "programado",
      "fonte": "SIROS/ANAC",
      "rota": "SBBE",
      "rota_nome": "Belem"
    },
    {
      "callsign": "AZU9585",
      "numero_voo": "9585",
      "airline_icao": "AZU",
      "airline": "Azul",
      "equipamento_icao": "AT76",
      "equipamento": "ATR 72",
      "assentos": "70",
      "etapa": "1",
      "tipo_operacao": "Domestico",
      "tipo_servico": "NÃO REGULAR DE PASSAGEIROS DOMÉSTICA",
      "origem_icao": "SBEG",
      "destino_icao": "SBUY",
      "partida_iso": "2026-05-20T09:15:00-03:00",
      "chegada_iso": "2026-05-20T11:05:00-03:00",
      "partida_brt": "09:15",
      "chegada_brt": "11:05",
      "status": "programado",
      "fonte": "SIROS/ANAC",
      "rota": "SBUY",
      "rota_nome": "SBUY"
    },
    {
      "callsign": "AZU4468",
      "numero_voo": "4468",
      "airline_icao": "AZU",
      "airline": "Azul",
      "equipamento_icao": "AT76",
      "equipamento": "ATR 72",
      "assentos": "70",
      "etapa": "1",
      "tipo_operacao": "Domestico",
      "tipo_servico": "REGULAR DE PASSAGEIROS DOMÉSTICA",
      "origem_icao": "SBEG",
      "destino_icao": "SWPI",
      "partida_iso": "2026-05-20T09:25:00-03:00",
      "chegada_iso": "2026-05-20T10:40:00-03:00",
      "partida_brt": "09:25",
      "chegada_brt": "10:40",
      "status": "programado",
      "fonte": "SIROS/ANAC",
      "rota": "SWPI",
      "rota_nome": "SWPI"
    },
    {
      "callsign": "TAM4510",
      "numero_voo": "4510",
      "airline_icao": "TAM",
      "airline": "LATAM",
      "equipamento_icao": "A321",
      "equipamento": "Airbus A321",
      "assentos": "224",
      "etapa": "1",
      "tipo_operacao": "Domestico",
      "tipo_servico": "REGULAR DE PASSAGEIROS DOMÉSTICA",
      "origem_icao": "SBEG",
      "destino_icao": "SBFZ",
      "partida_iso": "2026-05-20T09:25:00-03:00",
      "chegada_iso": "2026-05-20T12:50:00-03:00",
      "partida_brt": "09:25",
      "chegada_brt": "12:50",
      "status": "programado",
      "fonte": "SIROS/ANAC",
      "rota": "SBFZ",
      "rota_nome": "Fortaleza"
    },
    {
      "callsign": "LTG6559",
      "numero_voo": "6559",
      "airline_icao": "LTG",
      "airline": "LTG",
      "equipamento_icao": "B763",
      "equipamento": "Boeing 767-300",
      "assentos": "0",
      "etapa": "1",
      "tipo_operacao": "Domestico",
      "tipo_servico": "REGULAR DE CARGA DOMÉSTICA",
      "origem_icao": "SBEG",
      "destino_icao": "SBGR",
      "partida_iso": "2026-05-20T10:00:00-03:00",
      "chegada_iso": "2026-05-20T13:45:00-03:00",
      "partida_brt": "10:00",
      "chegada_brt": "13:45",
      "status": "programado",
      "fonte": "SIROS/ANAC",
      "rota": "SBGR",
      "rota_nome": "Sao Paulo / Guarulhos"
    },
    {
      "callsign": "GLO1782",
      "numero_voo": "1782",
      "airline_icao": "GLO",
      "airline": "GOL",
      "equipamento_icao": "B38M",
      "equipamento": "Boeing 737 MAX 8",
      "assentos": "186",
      "etapa": "2",
      "tipo_operacao": "Domestico",
      "tipo_servico": "REGULAR DE PASSAGEIROS DOMÉSTICA",
      "origem_icao": "SBEG",
      "destino_icao": "SBSN",
      "partida_iso": "2026-05-20T12:25:00-03:00",
      "chegada_iso": "2026-05-20T13:35:00-03:00",
      "partida_brt": "12:25",
      "chegada_brt": "13:35",
      "status": "programado",
      "fonte": "SIROS/ANAC",
      "rota": "SBSN",
      "rota_nome": "Santarem"
    },
    {
      "callsign": "AZU4022",
      "numero_voo": "4022",
      "airline_icao": "AZU",
      "airline": "Azul",
      "equipamento_icao": "A20N",
      "equipamento": "Airbus A320neo",
      "assentos": "174",
      "etapa": "1",
      "tipo_operacao": "Domestico",
      "tipo_servico": "REGULAR DE PASSAGEIROS DOMÉSTICA",
      "origem_icao": "SBEG",
      "destino_icao": "SBKP",
      "partida_iso": "2026-05-20T12:30:00-03:00",
      "chegada_iso": "2026-05-20T16:10:00-03:00",
      "partida_brt": "12:30",
      "chegada_brt": "16:10",
      "status": "programado",
      "fonte": "SIROS/ANAC",
      "rota": "SBKP",
      "rota_nome": "Campinas / Viracopos"
    },
    {
      "callsign": "TAM3469",
      "numero_voo": "3469",
      "airline_icao": "TAM",
      "airline": "LATAM",
      "equipamento_icao": "A321",
      "equipamento": "Airbus A321",
      "assentos": "224",
      "etapa": "1",
      "tipo_operacao": "Domestico",
      "tipo_servico": "REGULAR DE PASSAGEIROS DOMÉSTICA",
      "origem_icao": "SBEG",
      "destino_icao": "SBGR",
      "partida_iso": "2026-05-20T12:35:00-03:00",
      "chegada_iso": "2026-05-20T16:30:00-03:00",
      "partida_brt": "12:35",
      "chegada_brt": "16:30",
      "status": "programado",
      "fonte": "SIROS/ANAC",
      "rota": "SBGR",
      "rota_nome": "Sao Paulo / Guarulhos"
    },
    {
      "callsign": "TAM3749",
      "numero_voo": "3749",
      "airline_icao": "TAM",
      "airline": "LATAM",
      "equipamento_icao": "A320",
      "equipamento": "Airbus A320",
      "assentos": "180",
      "etapa": "1",
      "tipo_operacao": "Domestico",
      "tipo_servico": "REGULAR DE PASSAGEIROS DOMÉSTICA",
      "origem_icao": "SBEG",
      "destino_icao": "SBBR",
      "partida_iso": "2026-05-20T12:55:00-03:00",
      "chegada_iso": "2026-05-20T15:50:00-03:00",
      "partida_brt": "12:55",
      "chegada_brt": "15:50",
      "status": "programado",
      "fonte": "SIROS/ANAC",
      "rota": "SBBR",
      "rota_nome": "Brasilia"
    },
    {
      "callsign": "BPC6302",
      "numero_voo": "6302",
      "airline_icao": "BPC",
      "airline": "BPC",
      "equipamento_icao": "B734",
      "equipamento": "B734",
      "assentos": "0",
      "etapa": "1",
      "tipo_operacao": "Domestico",
      "tipo_servico": "NÃO REGULAR DE CARGA DOMÉSTICA",
      "origem_icao": "SBEG",
      "destino_icao": "SBKP",
      "partida_iso": "2026-05-20T13:00:00-03:00",
      "chegada_iso": "2026-05-20T17:00:00-03:00",
      "partida_brt": "13:00",
      "chegada_brt": "17:00",
      "status": "programado",
      "fonte": "SIROS/ANAC",
      "rota": "SBKP",
      "rota_nome": "Campinas / Viracopos"
    },
    {
      "callsign": "AZU2943",
      "numero_voo": "2943",
      "airline_icao": "AZU",
      "airline": "Azul",
      "equipamento_icao": "A20N",
      "equipamento": "Airbus A320neo",
      "assentos": "174",
      "etapa": "2",
      "tipo_operacao": "Domestico",
      "tipo_servico": "REGULAR DE PASSAGEIROS DOMÉSTICA",
      "origem_icao": "SBEG",
      "destino_icao": "SBBV",
      "partida_iso": "2026-05-20T13:10:00-03:00",
      "chegada_iso": "2026-05-20T14:25:00-03:00",
      "partida_brt": "13:10",
      "chegada_brt": "14:25",
      "status": "programado",
      "fonte": "SIROS/ANAC",
      "rota": "SBBV",
      "rota_nome": "Boa Vista"
    },
    {
      "callsign": "AZU4183",
      "numero_voo": "4183",
      "airline_icao": "AZU",
      "airline": "Azul",
      "equipamento_icao": "E195",
      "equipamento": "Embraer E195",
      "assentos": "118",
      "etapa": "1",
      "tipo_operacao": "Domestico",
      "tipo_servico": "REGULAR DE PASSAGEIROS DOMÉSTICA",
      "origem_icao": "SBEG",
      "destino_icao": "SBTF",
      "partida_iso": "2026-05-20T13:20:00-03:00",
      "chegada_iso": "2026-05-20T14:30:00-03:00",
      "partida_brt": "13:20",
      "chegada_brt": "14:30",
      "status": "programado",
      "fonte": "SIROS/ANAC",
      "rota": "SBTF",
      "rota_nome": "SBTF"
    },
    {
      "callsign": "ACN5313",
      "numero_voo": "5313",
      "airline_icao": "ACN",
      "airline": "ACN",
      "equipamento_icao": "C208",
      "equipamento": "C208",
      "assentos": "9",
      "etapa": "1",
      "tipo_operacao": "Domestico",
      "tipo_servico": "REGULAR DE PASSAGEIROS DOMÉSTICA",
      "origem_icao": "SBEG",
      "destino_icao": "SBMY",
      "partida_iso": "2026-05-20T13:35:00-03:00",
      "chegada_iso": "2026-05-20T15:05:00-03:00",
      "partida_brt": "13:35",
      "chegada_brt": "15:05",
      "status": "programado",
      "fonte": "SIROS/ANAC",
      "rota": "SBMY",
      "rota_nome": "SBMY"
    },
    {
      "callsign": "AZU4418",
      "numero_voo": "4418",
      "airline_icao": "AZU",
      "airline": "Azul",
      "equipamento_icao": "AT76",
      "equipamento": "ATR 72",
      "assentos": "70",
      "etapa": "1",
      "tipo_operacao": "Domestico",
      "tipo_servico": "REGULAR DE PASSAGEIROS DOMÉSTICA",
      "origem_icao": "SBEG",
      "destino_icao": "SBSN",
      "partida_iso": "2026-05-20T14:15:00-03:00",
      "chegada_iso": "2026-05-20T16:00:00-03:00",
      "partida_brt": "14:15",
      "chegada_brt": "16:00",
      "status": "programado",
      "fonte": "SIROS/ANAC",
      "rota": "SBSN",
      "rota_nome": "Santarem"
    },
    {
      "callsign": "GLO1783",
      "numero_voo": "1783",
      "airline_icao": "GLO",
      "airline": "GOL",
      "equipamento_icao": "B38M",
      "equipamento": "Boeing 737 MAX 8",
      "assentos": "186",
      "etapa": "2",
      "tipo_operacao": "Domestico",
      "tipo_servico": "REGULAR DE PASSAGEIROS DOMÉSTICA",
      "origem_icao": "SBEG",
      "destino_icao": "SBBR",
      "partida_iso": "2026-05-20T16:20:00-03:00",
      "chegada_iso": "2026-05-20T19:25:00-03:00",
      "partida_brt": "16:20",
      "chegada_brt": "19:25",
      "status": "programado",
      "fonte": "SIROS/ANAC",
      "rota": "SBBR",
      "rota_nome": "Brasilia"
    },
    {
      "callsign": "AZU9587",
      "numero_voo": "9587",
      "airline_icao": "AZU",
      "airline": "Azul",
      "equipamento_icao": "AT76",
      "equipamento": "ATR 72",
      "assentos": "70",
      "etapa": "1",
      "tipo_operacao": "Domestico",
      "tipo_servico": "NÃO REGULAR DE PASSAGEIROS DOMÉSTICA",
      "origem_icao": "SBEG",
      "destino_icao": "SBUY",
      "partida_iso": "2026-05-20T16:30:00-03:00",
      "chegada_iso": "2026-05-20T18:20:00-03:00",
      "partida_brt": "16:30",
      "chegada_brt": "18:20",
      "status": "programado",
      "fonte": "SIROS/ANAC",
      "rota": "SBUY",
      "rota_nome": "SBUY"
    },
    {
      "callsign": "AZU2683",
      "numero_voo": "2683",
      "airline_icao": "AZU",
      "airline": "Azul",
      "equipamento_icao": "E195",
      "equipamento": "Embraer E195",
      "assentos": "118",
      "etapa": "1",
      "tipo_operacao": "Domestico",
      "tipo_servico": "REGULAR DE PASSAGEIROS DOMÉSTICA",
      "origem_icao": "SBEG",
      "destino_icao": "SBTT",
      "partida_iso": "2026-05-20T16:50:00-03:00",
      "chegada_iso": "2026-05-20T18:40:00-03:00",
      "partida_brt": "16:50",
      "chegada_brt": "18:40",
      "status": "programado",
      "fonte": "SIROS/ANAC",
      "rota": "SBTT",
      "rota_nome": "SBTT"
    },
    {
      "callsign": "AZU4013",
      "numero_voo": "4013",
      "airline_icao": "AZU",
      "airline": "Azul",
      "equipamento_icao": "A20N",
      "equipamento": "Airbus A320neo",
      "assentos": "174",
      "etapa": "2",
      "tipo_operacao": "Domestico",
      "tipo_servico": "REGULAR DE PASSAGEIROS DOMÉSTICA",
      "origem_icao": "SBEG",
      "destino_icao": "SBKP",
      "partida_iso": "2026-05-20T17:15:00-03:00",
      "chegada_iso": "2026-05-20T20:55:00-03:00",
      "partida_brt": "17:15",
      "chegada_brt": "20:55",
      "status": "programado",
      "fonte": "SIROS/ANAC",
      "rota": "SBKP",
      "rota_nome": "Campinas / Viracopos"
    },
    {
      "callsign": "TAM3297",
      "numero_voo": "3297",
      "airline_icao": "TAM",
      "airline": "LATAM",
      "equipamento_icao": "A321",
      "equipamento": "Airbus A321",
      "assentos": "224",
      "etapa": "1",
      "tipo_operacao": "Domestico",
      "tipo_servico": "REGULAR DE PASSAGEIROS DOMÉSTICA",
      "origem_icao": "SBEG",
      "destino_icao": "SBGR",
      "partida_iso": "2026-05-20T17:20:00-03:00",
      "chegada_iso": "2026-05-20T21:25:00-03:00",
      "partida_brt": "17:20",
      "chegada_brt": "21:25",
      "status": "programado",
      "fonte": "SIROS/ANAC",
      "rota": "SBGR",
      "rota_nome": "Sao Paulo / Guarulhos"
    },
    {
      "callsign": "AZU2061",
      "numero_voo": "2061",
      "airline_icao": "AZU",
      "airline": "Azul",
      "equipamento_icao": "A21N",
      "equipamento": "Airbus A321neo",
      "assentos": "0",
      "etapa": "1",
      "tipo_operacao": "Domestico",
      "tipo_servico": "REGULAR DE CARGA DOMÉSTICA",
      "origem_icao": "SBEG",
      "destino_icao": "SBKP",
      "partida_iso": "2026-05-20T17:35:00-03:00",
      "chegada_iso": "2026-05-20T21:15:00-03:00",
      "partida_brt": "17:35",
      "chegada_brt": "21:15",
      "status": "programado",
      "fonte": "SIROS/ANAC",
      "rota": "SBKP",
      "rota_nome": "Campinas / Viracopos"
    },
    {
      "callsign": "AZU4163",
      "numero_voo": "4163",
      "airline_icao": "AZU",
      "airline": "Azul",
      "equipamento_icao": "A20N",
      "equipamento": "Airbus A320neo",
      "assentos": "174",
      "etapa": "1",
      "tipo_operacao": "Domestico",
      "tipo_servico": "REGULAR DE PASSAGEIROS DOMÉSTICA",
      "origem_icao": "SBEG",
      "destino_icao": "SBCF",
      "partida_iso": "2026-05-20T17:35:00-03:00",
      "chegada_iso": "2026-05-20T21:10:00-03:00",
      "partida_brt": "17:35",
      "chegada_brt": "21:10",
      "status": "programado",
      "fonte": "SIROS/ANAC",
      "rota": "SBCF",
      "rota_nome": "Belo Horizonte / Confins"
    },
    {
      "callsign": "TPA4057",
      "numero_voo": "4057",
      "airline_icao": "TPA",
      "airline": "TPA",
      "equipamento_icao": "A332",
      "equipamento": "Airbus A330-200",
      "assentos": "0",
      "etapa": "2",
      "tipo_operacao": "Internacional",
      "tipo_servico": "REGULAR DE CARGA INTERNACIONAL",
      "origem_icao": "SBEG",
      "destino_icao": "SKRG",
      "partida_iso": "2026-05-20T17:40:00-03:00",
      "chegada_iso": "2026-05-20T20:35:00-03:00",
      "partida_brt": "17:40",
      "chegada_brt": "20:35",
      "status": "programado",
      "fonte": "SIROS/ANAC",
      "rota": "SKRG",
      "rota_nome": "SKRG"
    },
    {
      "callsign": "TAP52",
      "numero_voo": "52",
      "airline_icao": "TAP",
      "airline": "TAP Portugal",
      "equipamento_icao": "A21N",
      "equipamento": "Airbus A321neo",
      "assentos": "168",
      "etapa": "1",
      "tipo_operacao": "Internacional",
      "tipo_servico": "REGULAR DE PASSAGEIROS INTERNACIONAL",
      "origem_icao": "SBEG",
      "destino_icao": "SBBE",
      "partida_iso": "2026-05-20T19:00:00-03:00",
      "chegada_iso": "2026-05-20T21:10:00-03:00",
      "partida_brt": "19:00",
      "chegada_brt": "21:10",
      "status": "programado",
      "fonte": "SIROS/ANAC",
      "rota": "SBBE",
      "rota_nome": "Belem"
    },
    {
      "callsign": "TAM3567",
      "numero_voo": "3567",
      "airline_icao": "TAM",
      "airline": "LATAM",
      "equipamento_icao": "A321",
      "equipamento": "Airbus A321",
      "assentos": "224",
      "etapa": "1",
      "tipo_operacao": "Domestico",
      "tipo_servico": "REGULAR DE PASSAGEIROS DOMÉSTICA",
      "origem_icao": "SBEG",
      "destino_icao": "SBGR",
      "partida_iso": "2026-05-20T19:20:00-03:00",
      "chegada_iso": "2026-05-20T23:10:00-03:00",
      "partida_brt": "19:20",
      "chegada_brt": "23:10",
      "status": "programado",
      "fonte": "SIROS/ANAC",
      "rota": "SBGR",
      "rota_nome": "Sao Paulo / Guarulhos"
    },
    {
      "callsign": "SID9304",
      "numero_voo": "9304",
      "airline_icao": "SID",
      "airline": "SID",
      "equipamento_icao": "B734",
      "equipamento": "B734",
      "assentos": "0",
      "etapa": "1",
      "tipo_operacao": "Domestico",
      "tipo_servico": "NÃO REGULAR DE CARGA DOMÉSTICA",
      "origem_icao": "SBEG",
      "destino_icao": "SBBR",
      "partida_iso": "2026-05-20T20:30:00-03:00",
      "chegada_iso": "2026-05-20T23:25:00-03:00",
      "partida_brt": "20:30",
      "chegada_brt": "23:25",
      "status": "programado",
      "fonte": "SIROS/ANAC",
      "rota": "SBBR",
      "rota_nome": "Brasilia"
    },
    {
      "callsign": "AZU4861",
      "numero_voo": "4861",
      "airline_icao": "AZU",
      "airline": "Azul",
      "equipamento_icao": "A20N",
      "equipamento": "Airbus A320neo",
      "assentos": "174",
      "etapa": "1",
      "tipo_operacao": "Domestico",
      "tipo_servico": "REGULAR DE PASSAGEIROS DOMÉSTICA",
      "origem_icao": "SBEG",
      "destino_icao": "SBBE",
      "partida_iso": "2026-05-20T20:35:00-03:00",
      "chegada_iso": "2026-05-20T22:40:00-03:00",
      "partida_brt": "20:35",
      "chegada_brt": "22:40",
      "status": "programado",
      "fonte": "SIROS/ANAC",
      "rota": "SBBE",
      "rota_nome": "Belem"
    },
    {
      "callsign": "GLO9610",
      "numero_voo": "9610",
      "airline_icao": "GLO",
      "airline": "GOL",
      "equipamento_icao": "B738",
      "equipamento": "Boeing 737-800",
      "assentos": "0",
      "etapa": "3",
      "tipo_operacao": "Domestico",
      "tipo_servico": "REGULAR DE CARGA DOMÉSTICA",
      "origem_icao": "SBEG",
      "destino_icao": "SBGR",
      "partida_iso": "2026-05-21T01:05:00-03:00",
      "chegada_iso": "2026-05-21T04:50:00-03:00",
      "partida_brt": "01:05",
      "chegada_brt": "04:50",
      "status": "programado",
      "fonte": "SIROS/ANAC",
      "rota": "SBGR",
      "rota_nome": "Sao Paulo / Guarulhos"
    }
  ]
}