{
  "updated_at": "2026-05-20T14:51:36.108524+00:00",
  "data_referencia": "2026-05-20",
  "airport_icao": "SBMQ",
  "airport_name": "Macapa",
  "airport_info": {
    "sg_aerodromo_icao": "SBMQ",
    "sg_aerodromo_iata": "MCP",
    "descricao": "ALBERTO ALCOLUMBRE - MACAPÁ - AP - BRASIL"
  },
  "source": "SIROS/ANAC",
  "source_url": "https://sas.anac.gov.br/sas/siros_api/",
  "arrivals": [
    {
      "callsign": "TAM3571",
      "numero_voo": "3571",
      "airline_icao": "TAM",
      "airline": "LATAM",
      "equipamento_icao": "A320",
      "equipamento": "Airbus A320",
      "assentos": "180",
      "etapa": "1",
      "tipo_operacao": "Domestico",
      "tipo_servico": "REGULAR DE PASSAGEIROS DOMÉSTICA",
      "origem_icao": "SBBE",
      "destino_icao": "SBMQ",
      "partida_iso": "2026-05-20T00:20:00-03:00",
      "chegada_iso": "2026-05-20T01:15:00-03:00",
      "partida_brt": "00:20",
      "chegada_brt": "01:15",
      "status": "programado",
      "fonte": "SIROS/ANAC",
      "rota": "SBBE",
      "rota_nome": "Belem"
    },
    {
      "callsign": "TAM3768",
      "numero_voo": "3768",
      "airline_icao": "TAM",
      "airline": "LATAM",
      "equipamento_icao": "A320",
      "equipamento": "Airbus A320",
      "assentos": "180",
      "etapa": "1",
      "tipo_operacao": "Domestico",
      "tipo_servico": "REGULAR DE PASSAGEIROS DOMÉSTICA",
      "origem_icao": "SBBR",
      "destino_icao": "SBMQ",
      "partida_iso": "2026-05-19T23:45:00-03:00",
      "chegada_iso": "2026-05-20T02:30:00-03:00",
      "partida_brt": "23:45",
      "chegada_brt": "02:30",
      "status": "programado",
      "fonte": "SIROS/ANAC",
      "rota": "SBBR",
      "rota_nome": "Brasilia"
    },
    {
      "callsign": "AZU4234",
      "numero_voo": "4234",
      "airline_icao": "AZU",
      "airline": "Azul",
      "equipamento_icao": "A20N",
      "equipamento": "Airbus A320neo",
      "assentos": "174",
      "etapa": "1",
      "tipo_operacao": "Domestico",
      "tipo_servico": "REGULAR DE PASSAGEIROS DOMÉSTICA",
      "origem_icao": "SBBE",
      "destino_icao": "SBMQ",
      "partida_iso": "2026-05-20T02:15:00-03:00",
      "chegada_iso": "2026-05-20T03:10:00-03:00",
      "partida_brt": "02:15",
      "chegada_brt": "03:10",
      "status": "programado",
      "fonte": "SIROS/ANAC",
      "rota": "SBBE",
      "rota_nome": "Belem"
    },
    {
      "callsign": "AZU4784",
      "numero_voo": "4784",
      "airline_icao": "AZU",
      "airline": "Azul",
      "equipamento_icao": "AT76",
      "equipamento": "ATR 72",
      "assentos": "70",
      "etapa": "1",
      "tipo_operacao": "Domestico",
      "tipo_servico": "REGULAR DE PASSAGEIROS DOMÉSTICA",
      "origem_icao": "SBBE",
      "destino_icao": "SBMQ",
      "partida_iso": "2026-05-20T06:25:00-03:00",
      "chegada_iso": "2026-05-20T07:35:00-03:00",
      "partida_brt": "06:25",
      "chegada_brt": "07:35",
      "status": "programado",
      "fonte": "SIROS/ANAC",
      "rota": "SBBE",
      "rota_nome": "Belem"
    },
    {
      "callsign": "AZU9591",
      "numero_voo": "9591",
      "airline_icao": "AZU",
      "airline": "Azul",
      "equipamento_icao": "AT76",
      "equipamento": "ATR 72",
      "assentos": "70",
      "etapa": "1",
      "tipo_operacao": "Domestico",
      "tipo_servico": "NÃO REGULAR DE PASSAGEIROS DOMÉSTICA",
      "origem_icao": "SBOI",
      "destino_icao": "SBMQ",
      "partida_iso": "2026-05-20T10:05:00-03:00",
      "chegada_iso": "2026-05-20T11:20:00-03:00",
      "partida_brt": "10:05",
      "chegada_brt": "11:20",
      "status": "programado",
      "fonte": "SIROS/ANAC",
      "rota": "SBOI",
      "rota_nome": "SBOI"
    },
    {
      "callsign": "TAM3860",
      "numero_voo": "3860",
      "airline_icao": "TAM",
      "airline": "LATAM",
      "equipamento_icao": "A320",
      "equipamento": "Airbus A320",
      "assentos": "180",
      "etapa": "1",
      "tipo_operacao": "Domestico",
      "tipo_servico": "REGULAR DE PASSAGEIROS DOMÉSTICA",
      "origem_icao": "SBGR",
      "destino_icao": "SBMQ",
      "partida_iso": "2026-05-20T09:20:00-03:00",
      "chegada_iso": "2026-05-20T13:15:00-03:00",
      "partida_brt": "09:20",
      "chegada_brt": "13:15",
      "status": "programado",
      "fonte": "SIROS/ANAC",
      "rota": "SBGR",
      "rota_nome": "Sao Paulo / Guarulhos"
    },
    {
      "callsign": "GLO2006",
      "numero_voo": "2006",
      "airline_icao": "GLO",
      "airline": "GOL",
      "equipamento_icao": "B38M",
      "equipamento": "Boeing 737 MAX 8",
      "assentos": "186",
      "etapa": "2",
      "tipo_operacao": "Domestico",
      "tipo_servico": "REGULAR DE PASSAGEIROS DOMÉSTICA",
      "origem_icao": "SBBE",
      "destino_icao": "SBMQ",
      "partida_iso": "2026-05-20T12:45:00-03:00",
      "chegada_iso": "2026-05-20T13:40:00-03:00",
      "partida_brt": "12:45",
      "chegada_brt": "13:40",
      "status": "programado",
      "fonte": "SIROS/ANAC",
      "rota": "SBBE",
      "rota_nome": "Belem"
    },
    {
      "callsign": "AZU4840",
      "numero_voo": "4840",
      "airline_icao": "AZU",
      "airline": "Azul",
      "equipamento_icao": "A20N",
      "equipamento": "Airbus A320neo",
      "assentos": "174",
      "etapa": "2",
      "tipo_operacao": "Domestico",
      "tipo_servico": "REGULAR DE PASSAGEIROS DOMÉSTICA",
      "origem_icao": "SBBE",
      "destino_icao": "SBMQ",
      "partida_iso": "2026-05-20T13:00:00-03:00",
      "chegada_iso": "2026-05-20T13:55:00-03:00",
      "partida_brt": "13:00",
      "chegada_brt": "13:55",
      "status": "programado",
      "fonte": "SIROS/ANAC",
      "rota": "SBBE",
      "rota_nome": "Belem"
    },
    {
      "callsign": "TAM3899",
      "numero_voo": "3899",
      "airline_icao": "TAM",
      "airline": "LATAM",
      "equipamento_icao": "A320",
      "equipamento": "Airbus A320",
      "assentos": "180",
      "etapa": "1",
      "tipo_operacao": "Domestico",
      "tipo_servico": "REGULAR DE PASSAGEIROS DOMÉSTICA",
      "origem_icao": "SBBE",
      "destino_icao": "SBMQ",
      "partida_iso": "2026-05-20T15:35:00-03:00",
      "chegada_iso": "2026-05-20T16:30:00-03:00",
      "partida_brt": "15:35",
      "chegada_brt": "16:30",
      "status": "programado",
      "fonte": "SIROS/ANAC",
      "rota": "SBBE",
      "rota_nome": "Belem"
    },
    {
      "callsign": "AZU9595",
      "numero_voo": "9595",
      "airline_icao": "AZU",
      "airline": "Azul",
      "equipamento_icao": "AT76",
      "equipamento": "ATR 72",
      "assentos": "70",
      "etapa": "1",
      "tipo_operacao": "Domestico",
      "tipo_servico": "NÃO REGULAR DE PASSAGEIROS DOMÉSTICA",
      "origem_icao": "SBOI",
      "destino_icao": "SBMQ",
      "partida_iso": "2026-05-20T17:30:00-03:00",
      "chegada_iso": "2026-05-20T18:45:00-03:00",
      "partida_brt": "17:30",
      "chegada_brt": "18:45",
      "status": "programado",
      "fonte": "SIROS/ANAC",
      "rota": "SBOI",
      "rota_nome": "SBOI"
    }
  ],
  "departures": [
    {
      "callsign": "TAM3570",
      "numero_voo": "3570",
      "airline_icao": "TAM",
      "airline": "LATAM",
      "equipamento_icao": "A320",
      "equipamento": "Airbus A320",
      "assentos": "180",
      "etapa": "1",
      "tipo_operacao": "Domestico",
      "tipo_servico": "REGULAR DE PASSAGEIROS DOMÉSTICA",
      "origem_icao": "SBMQ",
      "destino_icao": "SBBE",
      "partida_iso": "2026-05-20T02:35:00-03:00",
      "chegada_iso": "2026-05-20T03:30:00-03:00",
      "partida_brt": "02:35",
      "chegada_brt": "03:30",
      "status": "programado",
      "fonte": "SIROS/ANAC",
      "rota": "SBBE",
      "rota_nome": "Belem"
    },
    {
      "callsign": "TAM3769",
      "numero_voo": "3769",
      "airline_icao": "TAM",
      "airline": "LATAM",
      "equipamento_icao": "A320",
      "equipamento": "Airbus A320",
      "assentos": "180",
      "etapa": "1",
      "tipo_operacao": "Domestico",
      "tipo_servico": "REGULAR DE PASSAGEIROS DOMÉSTICA",
      "origem_icao": "SBMQ",
      "destino_icao": "SBBR",
      "partida_iso": "2026-05-20T03:10:00-03:00",
      "chegada_iso": "2026-05-20T05:55:00-03:00",
      "partida_brt": "03:10",
      "chegada_brt": "05:55",
      "status": "programado",
      "fonte": "SIROS/ANAC",
      "rota": "SBBR",
      "rota_nome": "Brasilia"
    },
    {
      "callsign": "AZU4235",
      "numero_voo": "4235",
      "airline_icao": "AZU",
      "airline": "Azul",
      "equipamento_icao": "A20N",
      "equipamento": "Airbus A320neo",
      "assentos": "174",
      "etapa": "1",
      "tipo_operacao": "Domestico",
      "tipo_servico": "REGULAR DE PASSAGEIROS DOMÉSTICA",
      "origem_icao": "SBMQ",
      "destino_icao": "SBBE",
      "partida_iso": "2026-05-20T03:50:00-03:00",
      "chegada_iso": "2026-05-20T04:45:00-03:00",
      "partida_brt": "03:50",
      "chegada_brt": "04:45",
      "status": "programado",
      "fonte": "SIROS/ANAC",
      "rota": "SBBE",
      "rota_nome": "Belem"
    },
    {
      "callsign": "AZU9590",
      "numero_voo": "9590",
      "airline_icao": "AZU",
      "airline": "Azul",
      "equipamento_icao": "AT76",
      "equipamento": "ATR 72",
      "assentos": "70",
      "etapa": "1",
      "tipo_operacao": "Domestico",
      "tipo_servico": "NÃO REGULAR DE PASSAGEIROS DOMÉSTICA",
      "origem_icao": "SBMQ",
      "destino_icao": "SBOI",
      "partida_iso": "2026-05-20T08:05:00-03:00",
      "chegada_iso": "2026-05-20T09:20:00-03:00",
      "partida_brt": "08:05",
      "chegada_brt": "09:20",
      "status": "programado",
      "fonte": "SIROS/ANAC",
      "rota": "SBOI",
      "rota_nome": "SBOI"
    },
    {
      "callsign": "TAM3898",
      "numero_voo": "3898",
      "airline_icao": "TAM",
      "airline": "LATAM",
      "equipamento_icao": "A320",
      "equipamento": "Airbus A320",
      "assentos": "180",
      "etapa": "1",
      "tipo_operacao": "Domestico",
      "tipo_servico": "REGULAR DE PASSAGEIROS DOMÉSTICA",
      "origem_icao": "SBMQ",
      "destino_icao": "SBBE",
      "partida_iso": "2026-05-20T13:55:00-03:00",
      "chegada_iso": "2026-05-20T14:50:00-03:00",
      "partida_brt": "13:55",
      "chegada_brt": "14:50",
      "status": "programado",
      "fonte": "SIROS/ANAC",
      "rota": "SBBE",
      "rota_nome": "Belem"
    },
    {
      "callsign": "AZU2705",
      "numero_voo": "2705",
      "airline_icao": "AZU",
      "airline": "Azul",
      "equipamento_icao": "A20N",
      "equipamento": "Airbus A320neo",
      "assentos": "174",
      "etapa": "1",
      "tipo_operacao": "Domestico",
      "tipo_servico": "REGULAR DE PASSAGEIROS DOMÉSTICA",
      "origem_icao": "SBMQ",
      "destino_icao": "SBBE",
      "partida_iso": "2026-05-20T14:35:00-03:00",
      "chegada_iso": "2026-05-20T15:30:00-03:00",
      "partida_brt": "14:35",
      "chegada_brt": "15:30",
      "status": "programado",
      "fonte": "SIROS/ANAC",
      "rota": "SBBE",
      "rota_nome": "Belem"
    },
    {
      "callsign": "GLO2007",
      "numero_voo": "2007",
      "airline_icao": "GLO",
      "airline": "GOL",
      "equipamento_icao": "B38M",
      "equipamento": "Boeing 737 MAX 8",
      "assentos": "186",
      "etapa": "1",
      "tipo_operacao": "Domestico",
      "tipo_servico": "REGULAR DE PASSAGEIROS DOMÉSTICA",
      "origem_icao": "SBMQ",
      "destino_icao": "SBBE",
      "partida_iso": "2026-05-20T15:00:00-03:00",
      "chegada_iso": "2026-05-20T16:00:00-03:00",
      "partida_brt": "15:00",
      "chegada_brt": "16:00",
      "status": "programado",
      "fonte": "SIROS/ANAC",
      "rota": "SBBE",
      "rota_nome": "Belem"
    },
    {
      "callsign": "AZU9594",
      "numero_voo": "9594",
      "airline_icao": "AZU",
      "airline": "Azul",
      "equipamento_icao": "AT76",
      "equipamento": "ATR 72",
      "assentos": "70",
      "etapa": "1",
      "tipo_operacao": "Domestico",
      "tipo_servico": "NÃO REGULAR DE PASSAGEIROS DOMÉSTICA",
      "origem_icao": "SBMQ",
      "destino_icao": "SBOI",
      "partida_iso": "2026-05-20T15:35:00-03:00",
      "chegada_iso": "2026-05-20T16:50:00-03:00",
      "partida_brt": "15:35",
      "chegada_brt": "16:50",
      "status": "programado",
      "fonte": "SIROS/ANAC",
      "rota": "SBOI",
      "rota_nome": "SBOI"
    },
    {
      "callsign": "TAM3861",
      "numero_voo": "3861",
      "airline_icao": "TAM",
      "airline": "LATAM",
      "equipamento_icao": "A320",
      "equipamento": "Airbus A320",
      "assentos": "180",
      "etapa": "1",
      "tipo_operacao": "Domestico",
      "tipo_servico": "REGULAR DE PASSAGEIROS DOMÉSTICA",
      "origem_icao": "SBMQ",
      "destino_icao": "SBGR",
      "partida_iso": "2026-05-20T17:15:00-03:00",
      "chegada_iso": "2026-05-20T21:10:00-03:00",
      "partida_brt": "17:15",
      "chegada_brt": "21:10",
      "status": "programado",
      "fonte": "SIROS/ANAC",
      "rota": "SBGR",
      "rota_nome": "Sao Paulo / Guarulhos"
    }
  ]
}